odoo/addons/sale_partner_version/README.rst
odoo/addons/sale_partner_version/__init__.py
odoo/addons/sale_partner_version/__manifest__.py
odoo/addons/sale_partner_version/i18n/sale_partner_version.pot
odoo/addons/sale_partner_version/models/__init__.py
odoo/addons/sale_partner_version/models/sale.py
odoo/addons/sale_partner_version/readme/CONTRIBUTORS.rst
odoo/addons/sale_partner_version/readme/DESCRIPTION.rst
odoo/addons/sale_partner_version/static/description/icon.png
odoo/addons/sale_partner_version/static/description/index.html
odoo/addons/sale_partner_version/tests/__init__.py
odoo/addons/sale_partner_version/tests/test_sale_partner_version.py
odoo14_addon_sale_partner_version-14.0.2.0.0.dist-info/METADATA
odoo14_addon_sale_partner_version-14.0.2.0.0.dist-info/WHEEL
odoo14_addon_sale_partner_version-14.0.2.0.0.dist-info/top_level.txt
odoo14_addon_sale_partner_version-14.0.2.0.0.dist-info/RECORD
